{
  "docs": {
    "General": [
      "gettingStarted",
      "crustOverview",
      "crustGrants",
      "claims",
      "claimsLockedCRU",
      "crustWallet",
      "glossary",
      "parameters",
      "contributing"
    ],
    "Learn": [
      "crustAccount",
      "crustTokens",
      "newBond",
      "guarantor",
      "validator",
      "GPoS",
      "sWorker",
      {
        "type": "subcategory",
        "label": "sWorker",
        "ids": [
          "sWorkerOverview"
        ]
      },
      "DSM",
      "storageMerchant",
      "identity"
    ],
    "Build": [
      "buildGettingStarted",
      "buildNode"
    ],
    "Node": [
      "nodeOverview",
      "nodeHardwareSpec",
      "ownerNode",
      "memberNode",
      "isolationNode",
      "validatorGuidance",
      "guarantorGuidance",
      "nodeBenefits",
      "nodeQos"
    ],
    "Storage": [
      "storageOverview"
    ]
  }
}
